[
  {
    "name": "Senso-ji Temple",
    "type": "landmark",
    "lat": 35.7148,
    "lng": 139.7967,
    "address": "2-3-1 Asakusa, Taito City, Tokyo",
    "tags": ["history", "culture", "art"],
    "avg_cost": "budget",
    "duration_minutes": 90,
    "open_hours": "06:00-17:00",
    "description": "Tokyo's oldest and most iconic temple, approached through the Nakamise shopping street. Go early morning to see it in near-solitude before the crowds arrive."
  },
  {
    "name": "Shibuya Crossing",
    "type": "attraction",
    "lat": 35.6595,
    "lng": 139.7004,
    "address": "2 Chome-2-1 Dogenzaka, Shibuya City, Tokyo",
    "tags": ["culture", "sightseeing"],
    "avg_cost": "budget",
    "duration_minutes": 45,
    "open_hours": "00:00-23:59",
    "description": "The world's busiest pedestrian crossing — best experienced from the Starbucks or Mag's Park overlook. In the evening rush it feels almost choreographed."
  },
  {
    "name": "Tsukiji Outer Market",
    "type": "restaurant",
    "lat": 35.6654,
    "lng": 139.7706,
    "address": "4-16-2 Tsukiji, Chuo City, Tokyo",
    "tags": ["food", "culture"],
    "avg_cost": "budget",
    "duration_minutes": 90,
    "open_hours": "05:00-14:00",
    "description": "The vendors and sushi stalls that spilled out from the old wholesale market. Tuna skewers, tamagoyaki, fresh oysters — one of the best breakfast walks anywhere."
  },
  {
    "name": "Meiji Shrine",
    "type": "landmark",
    "lat": 35.6764,
    "lng": 139.6993,
    "address": "1-1 Yoyogikamizonocho, Shibuya City, Tokyo",
    "tags": ["history", "nature", "culture"],
    "avg_cost": "budget",
    "duration_minutes": 75,
    "open_hours": "05:00-18:00",
    "description": "A forested Shinto shrine in the heart of the city — the walk through the towering torii gate and camphor forest is a genuine decompression from urban Tokyo."
  },
  {
    "name": "teamLab Planets",
    "type": "attraction",
    "lat": 35.6464,
    "lng": 139.7852,
    "address": "6-1-16 Toyosu, Koto City, Tokyo",
    "tags": ["art", "adventure"],
    "avg_cost": "mid-range",
    "duration_minutes": 90,
    "open_hours": "10:00-21:00",
    "description": "Walk barefoot through rooms of infinite digital flowers, light forests, and a room that's entirely mirrors and koi fish. Immersive doesn't begin to cover it. Book ahead."
  },
  {
    "name": "Shinjuku Gyoen National Garden",
    "type": "park",
    "lat": 35.6852,
    "lng": 139.7100,
    "address": "11 Naito-machi, Shinjuku City, Tokyo",
    "tags": ["nature", "sightseeing"],
    "avg_cost": "budget",
    "duration_minutes": 90,
    "open_hours": "09:00-16:30",
    "description": "Three distinct gardens — French formal, English landscape, Japanese traditional — across 58 beautiful hectares. In spring the cherry blossoms here are among Tokyo's finest."
  },
  {
    "name": "Akihabara Electric Town",
    "type": "attraction",
    "lat": 35.7023,
    "lng": 139.7745,
    "address": "Akihabara, Taito City, Tokyo",
    "tags": ["culture", "adventure"],
    "avg_cost": "mid-range",
    "duration_minutes": 120,
    "open_hours": "10:00-21:00",
    "description": "Multi-story electronics shops, anime figure stores, maid cafés, and retro game arcades in every direction. Even if none of that is your thing, it's unlike anywhere else."
  },
  {
    "name": "Harajuku Takeshita Street",
    "type": "attraction",
    "lat": 35.6717,
    "lng": 139.7036,
    "address": "1 Chome-17-5 Jingumae, Shibuya City, Tokyo",
    "tags": ["culture", "art", "food"],
    "avg_cost": "budget",
    "duration_minutes": 60,
    "open_hours": "10:00-20:00",
    "description": "Tokyo's youth fashion epicentre — crepe stands, costume shops, and street styles you genuinely won't find anywhere else. Weekends are absolute controlled chaos."
  },
  {
    "name": "Tokyo National Museum",
    "type": "museum",
    "lat": 35.7189,
    "lng": 139.7763,
    "address": "13-9 Uenokoen, Taito City, Tokyo",
    "tags": ["history", "art", "culture"],
    "avg_cost": "budget",
    "duration_minutes": 150,
    "open_hours": "09:30-17:00",
    "description": "Japan's oldest and largest museum — samurai armour, Buddhist sculpture, ukiyo-e prints, tea ceremony objects. More than 110,000 items; pick one or two buildings and go deep."
  },
  {
    "name": "Odaiba Waterfront",
    "type": "attraction",
    "lat": 35.6267,
    "lng": 139.7760,
    "address": "Odaiba, Minato City, Tokyo",
    "tags": ["sightseeing", "adventure"],
    "avg_cost": "budget",
    "duration_minutes": 90,
    "open_hours": "08:00-22:00",
    "description": "An artificial island in Tokyo Bay with a miniature Statue of Liberty, the Rainbow Bridge, and the best skyline view of the city — especially photogenic at night."
  },
  {
    "name": "Yanaka Old Town Walk",
    "type": "attraction",
    "lat": 35.7272,
    "lng": 139.7664,
    "address": "Yanaka, Taito City, Tokyo",
    "tags": ["history", "culture", "sightseeing"],
    "avg_cost": "budget",
    "duration_minutes": 90,
    "open_hours": "09:00-18:00",
    "description": "The neighbourhood that survived the war and earthquakes — narrow shopping streets, old wooden temples, cats everywhere. Feels like stepping back fifty years."
  },
  {
    "name": "Sushi Saito (Roppongi area)",
    "type": "restaurant",
    "lat": 35.6627,
    "lng": 139.7253,
    "address": "1-9-15 Azabudai, Minato City, Tokyo",
    "tags": ["food"],
    "avg_cost": "luxury",
    "duration_minutes": 90,
    "open_hours": "12:00-14:00,18:00-21:00",
    "description": "One of the most coveted sushi counters in Japan — 12 seats, Edomae-style, each piece arriving at exactly the right temperature. Near-impossible reservations, transcendent food."
  },
  {
    "name": "Ichiran Ramen Shibuya",
    "type": "restaurant",
    "lat": 35.6607,
    "lng": 139.6987,
    "address": "B1F Beam Bldg, 31-2 Udagawacho, Shibuya, Tokyo",
    "tags": ["food"],
    "avg_cost": "budget",
    "duration_minutes": 45,
    "open_hours": "10:00-23:00",
    "description": "Solo ramen dining in individual booths — you customise every element (broth richness, noodle texture, garlic level) on a form. Introvert's paradise, genuinely great tonkotsu."
  },
  {
    "name": "Torishiki Yakitori",
    "type": "restaurant",
    "lat": 35.6520,
    "lng": 139.7018,
    "address": "2-14-12 Kami-Osaki, Shinagawa City, Tokyo",
    "tags": ["food"],
    "avg_cost": "mid-range",
    "duration_minutes": 90,
    "open_hours": "17:00-22:00",
    "description": "Michelin-starred yakitori counter — Yoshiteru Ikegawa grills every skewer himself, from chicken heart to tsukune. Counter seats only; reserve well ahead."
  },
  {
    "name": "Depachika at Isetan Shinjuku",
    "type": "restaurant",
    "lat": 35.6897,
    "lng": 139.7023,
    "address": "3-14-1 Shinjuku, Shinjuku City, Tokyo",
    "tags": ["food", "culture"],
    "avg_cost": "mid-range",
    "duration_minutes": 60,
    "open_hours": "10:00-20:00",
    "description": "The basement food hall of Japan's most famous department store — bento boxes, wagashi sweets, sashimi counters, pastries from Tokyo's top bakeries. An underrated Tokyo ritual."
  },
  {
    "name": "Ryogoku Sumo Stadium",
    "type": "attraction",
    "lat": 35.6974,
    "lng": 139.7939,
    "address": "1-3-28 Yokoami, Sumida City, Tokyo",
    "tags": ["culture", "history"],
    "avg_cost": "mid-range",
    "duration_minutes": 240,
    "open_hours": "08:00-18:00",
    "description": "Tournament weeks (January, May, September) let you watch sumo all day — get cheap upper seats and move down as matches get better. Even the practice (keiko) sessions are fascinating."
  },
  {
    "name": "Tokyo Skytree",
    "type": "landmark",
    "lat": 35.7101,
    "lng": 139.8107,
    "address": "1-1-2 Oshiage, Sumida City, Tokyo",
    "tags": ["sightseeing", "adventure"],
    "avg_cost": "mid-range",
    "duration_minutes": 90,
    "open_hours": "10:00-21:00",
    "description": "The world's tallest tower at 634 metres — the view from the Tembo Deck at 350m covers the entire Kanto plain on a clear day, and all the way to Mount Fuji."
  },
  {
    "name": "Nezu Shrine",
    "type": "landmark",
    "lat": 35.7219,
    "lng": 139.7609,
    "address": "1-28-9 Nezu, Bunkyo City, Tokyo",
    "tags": ["history", "nature", "culture"],
    "avg_cost": "budget",
    "duration_minutes": 60,
    "open_hours": "06:00-17:00",
    "description": "Tokyo's answer to Kyoto's Fushimi Inari — a long row of red torii gates through forested grounds. Far less visited than it deserves to be."
  },
  {
    "name": "Shibuya Stream Rooftop & Scramble Square",
    "type": "attraction",
    "lat": 35.6577,
    "lng": 139.7026,
    "address": "2-24-12 Shibuya, Shibuya City, Tokyo",
    "tags": ["sightseeing", "nightlife"],
    "avg_cost": "mid-range",
    "duration_minutes": 60,
    "open_hours": "11:00-23:00",
    "description": "The Scramble Square observation deck at 229m directly above the famous crossing — the best urban viewpoint in Tokyo, especially as the city lights up at dusk."
  },
  {
    "name": "Koenji Retro Shopping Street",
    "type": "attraction",
    "lat": 35.7053,
    "lng": 139.6492,
    "address": "Koenji, Suginami City, Tokyo",
    "tags": ["culture", "nightlife", "art"],
    "avg_cost": "budget",
    "duration_minutes": 90,
    "open_hours": "11:00-21:00",
    "description": "Tokyo's bohemian neighbourhood — vintage clothing shops, record stores, live jazz bars, and ramen joints without the tourist markup. A locals' evening favourite."
  },
  {
    "name": "Mount Takao Day Trip",
    "type": "attraction",
    "lat": 35.6256,
    "lng": 139.2432,
    "address": "Takaomachi, Hachioji City, Tokyo",
    "tags": ["nature", "adventure"],
    "avg_cost": "budget",
    "duration_minutes": 240,
    "open_hours": "08:00-17:00",
    "description": "An hour from Shinjuku on the Keio line, Mt Takao offers forest trails, a monkey park, and a free-range cable car. On clear winter days you can see Fuji from the summit."
  },
  {
    "name": "Nakameguro Canal Walk",
    "type": "attraction",
    "lat": 35.6429,
    "lng": 139.6987,
    "address": "Nakameguro, Meguro City, Tokyo",
    "tags": ["nature", "nightlife", "food"],
    "avg_cost": "budget",
    "duration_minutes": 75,
    "open_hours": "09:00-23:00",
    "description": "The tree-lined Meguro River with independent coffee roasters, vintage boutiques, and tiny restaurants. In spring it becomes Tokyo's most photogenic cherry blossom tunnel."
  },
  {
    "name": "Roppongi Art Triangle",
    "type": "museum",
    "lat": 35.6641,
    "lng": 139.7277,
    "address": "Roppongi, Minato City, Tokyo",
    "tags": ["art", "culture"],
    "avg_cost": "mid-range",
    "duration_minutes": 120,
    "open_hours": "10:00-18:00",
    "description": "Mori Art Museum, National Art Center, and Suntory Museum of Art form a walkable triangle. The Mori in Roppongi Hills also has the city's best 360-degree view deck."
  },
  {
    "name": "Hamarikyu Gardens",
    "type": "park",
    "lat": 35.6600,
    "lng": 139.7638,
    "address": "1-1 Hamarikyuteien, Chuo City, Tokyo",
    "tags": ["nature", "history"],
    "avg_cost": "budget",
    "duration_minutes": 60,
    "open_hours": "09:00-17:00",
    "description": "A tidal garden at the edge of Tokyo Bay — the teahouse on the pond serves matcha with a wagashi sweet. The skyscrapers framing the old willow trees are a perfect Tokyo contrast."
  },
  {
    "name": "Shimokitazawa Music Scene",
    "type": "attraction",
    "lat": 35.6615,
    "lng": 139.6676,
    "address": "Shimokitazawa, Setagaya City, Tokyo",
    "tags": ["nightlife", "culture", "art"],
    "avg_cost": "budget",
    "duration_minutes": 120,
    "open_hours": "16:00-02:00",
    "description": "Tokyo's live music heartland — cramped basement venues, vinyl record shops, and theatre bars in every direction. The best neighbourhood in the city for a late night out."
  },
  {
    "name": "Tofu Restaurant Ukai Tofuya",
    "type": "restaurant",
    "lat": 35.6474,
    "lng": 139.7339,
    "address": "4-4-13 Shiba Koen, Minato City, Tokyo",
    "tags": ["food", "history"],
    "avg_cost": "luxury",
    "duration_minutes": 120,
    "open_hours": "11:00-20:00",
    "description": "Traditional kaiseki-style tofu cuisine in a series of tranquil tatami rooms with a Japanese garden. Right below Tokyo Tower. One of those once-in-a-trip experiences."
  }
]
